resource_backed_dask_array/__init__.py
resource_backed_dask_array/_test.py
resource_backed_dask_array/_version.py
resource_backed_dask_array-0.1.0.dist-info/LICENSE
resource_backed_dask_array-0.1.0.dist-info/METADATA
resource_backed_dask_array-0.1.0.dist-info/WHEEL
resource_backed_dask_array-0.1.0.dist-info/top_level.txt
resource_backed_dask_array-0.1.0.dist-info/RECORD
