Metadata-Version: 2.1
Name: resource_backed_dask_array
Version: 0.1.0
Summary: experimental Dask array that opens/closes a resource when computing
Home-page: https://github.com/tlambert03/resource-backed-dask-array
Author: Talley Lambert
Author-email: talley.lambert@gmail.com
License: BSD-3-Clause
Project-URL: Source Code, https://github.com/tlambert03/resource-backed-dask-array
Platform: UNKNOWN
Classifier: Development Status :: 3 - Alpha
Classifier: License :: OSI Approved :: BSD License
Classifier: Natural Language :: English
Classifier: Programming Language :: Python :: 3
Classifier: Programming Language :: Python :: 3 :: Only
Classifier: Programming Language :: Python :: 3.7
Classifier: Programming Language :: Python :: 3.8
Classifier: Programming Language :: Python :: 3.9
Classifier: Programming Language :: Python :: 3.10
Requires-Python: >=3.7
Provides-Extra: dev
Provides-Extra: testing
License-File: LICENSE
